ihepjob/__init__.py
ihepjob/_version.py
ihepjob/config_manager.py
ihepjob/job_runner.py
ihepjob/juno_filesystem.py
ihepjob/name_manager.py
ihepjob/prepare_submit.py
ihepjob/process_utility.py
ihepjob/single_job.py
ihepjob/templates/default/jobs.yaml.jinja
ihepjob/templates/default/project_config.yaml
ihepjob/templates/default/single_job.sh.jinja
ihepjob/templates/default/submit_job.sh.jinja
ihepjob-4.0.2.dist-info/METADATA
ihepjob-4.0.2.dist-info/WHEEL
ihepjob-4.0.2.dist-info/entry_points.txt
ihepjob-4.0.2.dist-info/top_level.txt
ihepjob-4.0.2.dist-info/RECORD
